Metadata-Version: 2.1
Name: herojson
Version: 0.0
Summary: um modúlo python criado para facilitar a manipulação de arquivos json
Home-page: https://github.com/EliseuGaspar/herojson
Author: Eliseu Gaspar
Author-email: Eliseu Gaspar <eliseugaspar4@gmail.com>
Project-URL: Código fonte, https://github.com/EliseuGaspar/herojson
Project-URL: Download, https://github.com/EliseuGaspar/herojson.git
Keywords: modúlo,json,hero
Classifier: Environment :: Console
Classifier: License :: OSI Approved :: MIT License
Classifier: Natural Language :: Portuguese
Classifier: Operating System :: OS Independent
Classifier: Programming Language :: Python :: 3
Classifier: Programming Language :: Python :: 3.9
Classifier: Programming Language :: Python :: 3.10
Classifier: Topic :: Utilities
Requires-Python: >=3.8
License-File: LICENCE.txt
